{
    "name": "root",
    "gauges": {
        "CubeAgent.Policy.Entropy.mean": {
            "value": 0.004894435405731201,
            "min": 7.939673196233343e-06,
            "max": 0.6826655864715576,
            "count": 655
        },
        "CubeAgent.Policy.Entropy.sum": {
            "value": 8.986183166503906,
            "min": 0.014863068237900734,
            "max": 1892.3489990234375,
            "count": 655
        },
        "CubeAgent.Environment.EpisodeLength.mean": {
            "value": 24.36842105263158,
            "min": 23.16867469879518,
            "max": 55.026315789473685,
            "count": 655
        },
        "CubeAgent.Environment.EpisodeLength.sum": {
            "value": 1852.0,
            "min": 1407.0,
            "max": 2161.0,
            "count": 655
        },
        "CubeAgent.Step.mean": {
            "value": 1309983.0,
            "min": 1971.0,
            "max": 1309983.0,
            "count": 655
        },
        "CubeAgent.Step.sum": {
            "value": 1309983.0,
            "min": 1971.0,
            "max": 1309983.0,
            "count": 655
        },
        "CubeAgent.Policy.ExtrinsicValueEstimate.mean": {
            "value": -2.638371467590332,
            "min": -20.400938034057617,
            "max": -2.0655863285064697,
            "count": 655
        },
        "CubeAgent.Policy.ExtrinsicValueEstimate.sum": {
            "value": -208.4313507080078,
            "min": -1060.8487548828125,
            "max": -163.1813201904297,
            "count": 655
        },
        "CubeAgent.Environment.CumulativeReward.mean": {
            "value": -3.0126582278481013,
            "min": -39.19047619047619,
            "max": -2.466666666666667,
            "count": 655
        },
        "CubeAgent.Environment.CumulativeReward.sum": {
            "value": -238.0,
            "min": -1646.0,
            "max": -178.0,
            "count": 655
        },
        "CubeAgent.Policy.ExtrinsicReward.mean": {
            "value": -3.0126582278481013,
            "min": -39.19047619047619,
            "max": -2.466666666666667,
            "count": 655
        },
        "CubeAgent.Policy.ExtrinsicReward.sum": {
            "value": -238.0,
            "min": -1646.0,
            "max": -178.0,
            "count": 655
        },
        "CubeAgent.Losses.PolicyLoss.mean": {
            "value": 0.250926341891029,
            "min": 0.21926947681204564,
            "max": 0.3700637447147015,
            "count": 655
        },
        "CubeAgent.Losses.PolicyLoss.sum": {
            "value": 2.5092634189102903,
            "min": 2.126166896098952,
            "max": 4.375915772656018,
            "count": 655
        },
        "CubeAgent.Losses.ValueLoss.mean": {
            "value": 0.2136609921033658,
            "min": 0.011482239240835258,
            "max": 93.69001992761697,
            "count": 655
        },
        "CubeAgent.Losses.ValueLoss.sum": {
            "value": 2.136609921033658,
            "min": 0.12630463164918784,
            "max": 1499.0403188418716,
            "count": 655
        },
        "CubeAgent.Policy.LearningRate.mean": {
            "value": 0.000221461508179506,
            "min": 0.000221461508179506,
            "max": 0.00029996140501286494,
            "count": 655
        },
        "CubeAgent.Policy.LearningRate.sum": {
            "value": 0.00221461508179506,
            "min": 0.00200292911235704,
            "max": 0.00479714058095314,
            "count": 655
        },
        "CubeAgent.Policy.Epsilon.mean": {
            "value": 0.17382049400000002,
            "min": 0.17382049400000002,
            "max": 0.199987135,
            "count": 655
        },
        "CubeAgent.Policy.Epsilon.sum": {
            "value": 1.7382049400000001,
            "min": 1.5676429600000001,
            "max": 3.19904686,
            "count": 655
        },
        "CubeAgent.Policy.Beta.mean": {
            "value": 0.0005000000000000001,
            "min": 0.0005,
            "max": 0.0005000000000000002,
            "count": 655
        },
        "CubeAgent.Policy.Beta.sum": {
            "value": 0.005000000000000001,
            "min": 0.004,
            "max": 0.008,
            "count": 655
        },
        "CubeAgent.IsTraining.mean": {
            "value": 1.0,
            "min": 1.0,
            "max": 1.0,
            "count": 655
        },
        "CubeAgent.IsTraining.sum": {
            "value": 1.0,
            "min": 1.0,
            "max": 1.0,
            "count": 655
        }
    },
    "metadata": {
        "timer_format_version": "0.1.0",
        "start_time_seconds": "1714150386",
        "python_version": "3.9.19 (main, Mar 21 2024, 17:21:27) [MSC v.1916 64 bit (AMD64)]",
        "command_line_arguments": "C:\\Users\\robwi\\anaconda3\\envs\\ML-Agents-Rob\\Scripts\\mlagents-learn config/CubeAgent.yaml --run-id=Main --force",
        "mlagents_version": "0.30.0",
        "mlagents_envs_version": "0.30.0",
        "communication_protocol_version": "1.5.0",
        "pytorch_version": "1.7.1+cu110",
        "numpy_version": "1.21.2",
        "end_time_seconds": "1714155706"
    },
    "total": 5320.0675738,
    "count": 1,
    "self": 0.009306699999797274,
    "children": {
        "run_training.setup": {
            "total": 0.09847209999999995,
            "count": 1,
            "self": 0.09847209999999995
        },
        "TrainerController.start_learning": {
            "total": 5319.959795,
            "count": 1,
            "self": 1.1966280000478946,
            "children": {
                "TrainerController._reset_env": {
                    "total": 9.4100283,
                    "count": 1,
                    "self": 9.4100283
                },
                "TrainerController.advance": {
                    "total": 5309.289261499952,
                    "count": 47962,
                    "self": 0.9466068999572599,
                    "children": {
                        "env_step": {
                            "total": 1190.5334089000055,
                            "count": 47962,
                            "self": 1092.207346300093,
                            "children": {
                                "SubprocessEnvManager._take_step": {
                                    "total": 97.66706349998248,
                                    "count": 47962,
                                    "self": 2.916212999956585,
                                    "children": {
                                        "TorchPolicy.evaluate": {
                                            "total": 94.75085050002589,
                                            "count": 36449,
                                            "self": 94.75085050002589
                                        }
                                    }
                                },
                                "workers": {
                                    "total": 0.6589990999299822,
                                    "count": 47961,
                                    "self": 0.0,
                                    "children": {
                                        "worker_root": {
                                            "total": 5249.841471899981,
                                            "count": 47961,
                                            "is_parallel": true,
                                            "self": 4302.326163600025,
                                            "children": {
                                                "steps_from_proto": {
                                                    "total": 0.0014498000000005007,
                                                    "count": 1,
                                                    "is_parallel": true,
                                                    "self": 0.0005650000000008149,
                                                    "children": {
                                                        "_process_rank_one_or_two_observation": {
                                                            "total": 0.0008847999999996858,
                                                            "count": 4,
                                                            "is_parallel": true,
                                                            "self": 0.0008847999999996858
                                                        }
                                                    }
                                                },
                                                "UnityEnvironment.step": {
                                                    "total": 947.5138584999556,
                                                    "count": 47961,
                                                    "is_parallel": true,
                                                    "self": 12.89097169994875,
                                                    "children": {
                                                        "UnityEnvironment._generate_step_input": {
                                                            "total": 15.614364200018619,
                                                            "count": 47961,
                                                            "is_parallel": true,
                                                            "self": 15.614364200018619
                                                        },
                                                        "communicator.exchange": {
                                                            "total": 890.5963811000086,
                                                            "count": 47961,
                                                            "is_parallel": true,
                                                            "self": 890.5963811000086
                                                        },
                                                        "steps_from_proto": {
                                                            "total": 28.412141499979725,
                                                            "count": 47961,
                                                            "is_parallel": true,
                                                            "self": 8.514904999794283,
                                                            "children": {
                                                                "_process_rank_one_or_two_observation": {
                                                                    "total": 19.897236500185443,
                                                                    "count": 191844,
                                                                    "is_parallel": true,
                                                                    "self": 19.897236500185443
                                                                }
                                                            }
                                                        }
                                                    }
                                                }
                                            }
                                        }
                                    }
                                }
                            }
                        },
                        "trainer_advance": {
                            "total": 4117.809245699989,
                            "count": 47961,
                            "self": 1.783686199953081,
                            "children": {
                                "process_trajectory": {
                                    "total": 164.82561620004068,
                                    "count": 47961,
                                    "self": 164.66107430004055,
                                    "children": {
                                        "RLTrainer._checkpoint": {
                                            "total": 0.16454190000013114,
                                            "count": 2,
                                            "self": 0.16454190000013114
                                        }
                                    }
                                },
                                "_update_policy": {
                                    "total": 3951.199943299996,
                                    "count": 7583,
                                    "self": 243.96057419998397,
                                    "children": {
                                        "TorchPPOOptimizer.update": {
                                            "total": 3707.239369100012,
                                            "count": 383214,
                                            "self": 3707.239369100012
                                        }
                                    }
                                }
                            }
                        }
                    }
                },
                "TrainerController._save_models": {
                    "total": 0.06387720000020636,
                    "count": 1,
                    "self": 0.008207500000025902,
                    "children": {
                        "RLTrainer._checkpoint": {
                            "total": 0.055669700000180455,
                            "count": 1,
                            "self": 0.055669700000180455
                        }
                    }
                }
            }
        }
    }
}